README.md
setup.py
earthscope/__init__.py
earthscope/backend.py
earthscope/package_version.py
earthscope.egg-info/PKG-INFO
earthscope.egg-info/SOURCES.txt
earthscope.egg-info/dependency_links.txt
earthscope.egg-info/entry_points.txt
earthscope.egg-info/requires.txt
earthscope.egg-info/top_level.txt
tileserver/__init__.py
tileserver/convert_to_rgb_8bit.py
tileserver/register_jupyter_endpoint.py
tileserver/tiff_io.py
tileserver/tiff_transform_cache.py
tileserver/tileserver.py
tileserver/transforms/__init__.py
tileserver/transforms/contrast_adjust.py
tileserver/transforms/convert_to_8bit.py
tileserver/transforms/convert_to_rgb.py
tileserver/transforms/fix_photoscan_nodata.py