Metadata-Version: 2.1
Name: earthscope
Version: 0.2.0
Summary: GeoTIFF viewer for JupyterLab
Home-page: https://github.com/ceresimaging/earthscope
Author: Seth Nickell
Author-email: snickell@gmail.com
License: MIT
Platform: UNKNOWN
Classifier: License :: OSI Approved :: MIT License
Classifier: Programming Language :: Python :: 3
Classifier: Programming Language :: Python :: 3.7
